actava_cli/__init__.py
actava_cli/__main__.py
actava_cli-0.1.1.dist-info/METADATA
actava_cli-0.1.1.dist-info/WHEEL
actava_cli-0.1.1.dist-info/entry_points.txt
actava_cli-0.1.1.dist-info/RECORD
