Metadata-Version: 2.4
Name: actava-cli
Version: 0.1.1
Summary: ActAVA CLI: Deploy and manage AI agents on ActAVA's managed cloud platform. Commercial offering for paid customers only.
Project-URL: Homepage, https://actava.ai
Project-URL: Documentation, https://docs.actava.ai
Project-URL: Repository, https://github.com/actava-ai/actava
Project-URL: Support, https://support.actava.ai
Project-URL: Bug Tracker, https://support.actava.ai/issues
Author-email: ActAVA <team@actava.ai>
Maintainer-email: ActAVA <team@actava.ai>
License: Proprietary
Keywords: agents,ai,cli,cloud,commercial,deployment,enterprise,healthcare,langchain,langgraph
Classifier: Development Status :: 4 - Beta
Classifier: Environment :: Console
Classifier: Intended Audience :: Developers
Classifier: Intended Audience :: Healthcare Industry
Classifier: Intended Audience :: System Administrators
Classifier: License :: Other/Proprietary License
Classifier: Operating System :: OS Independent
Classifier: Programming Language :: Python :: 3
Classifier: Programming Language :: Python :: 3.11
Classifier: Programming Language :: Python :: 3.12
Classifier: Topic :: Scientific/Engineering :: Artificial Intelligence
Classifier: Topic :: Software Development :: Libraries :: Python Modules
Classifier: Topic :: System :: Systems Administration
Requires-Python: >=3.11
Requires-Dist: actava~=0.1
Requires-Dist: pydantic>=2
Requires-Dist: pyyaml>=6
Requires-Dist: requests>=2.32
Requires-Dist: rich>=13
Requires-Dist: typer>=0.12
Requires-Dist: uvicorn>=0.30
Provides-Extra: dev
Requires-Dist: black>=23.0; extra == 'dev'
Requires-Dist: mypy>=1.0; extra == 'dev'
Requires-Dist: pre-commit>=3.0; extra == 'dev'
Requires-Dist: pytest-cov>=4.0; extra == 'dev'
Requires-Dist: pytest>=7.0; extra == 'dev'
Requires-Dist: ruff>=0.1.0; extra == 'dev'
